rand_convolve/__init__.py
rand_convolve/rand_c.py
rand_convolve-1.0.7.dist-info/LICENSE.md
rand_convolve-1.0.7.dist-info/METADATA
rand_convolve-1.0.7.dist-info/WHEEL
rand_convolve-1.0.7.dist-info/top_level.txt
rand_convolve-1.0.7.dist-info/RECORD
