Metadata-Version: 2.1
Name: rand-convolve
Version: 1.0.7
Summary: Runs a multi-random-kernel convolution on an image.
Home-page: https://github.com/aceynk/random_convolution
Author: aceynk
License: MIT
Project-URL: Issues, https://github.com/aceynk/random_convolution/issues
Classifier: Programming Language :: Python :: 3
Requires-Python: >=3.1
License-File: LICENSE.md
Requires-Dist: pillow
Requires-Dist: numpy
Requires-Dist: scipy
